{
  "project_info": {
    "project_number": "504843835361",
    "project_id": "messaging-supa",
    "storage_bucket": "messaging-supa.appspot.com"
  },
  "client": [
    {
      "client_info": {
        "mobilesdk_app_id": "1:504843835361:android:ea41f9130e4d6d1d9624a0",
        "android_client_info": {
          "package_name": "com.example.messaging_supabase"
        }
      },
      "oauth_client": [
        {
          "client_id": "504843835361-8ijobj1vi9mfdc2tpjanb5bllgcn17f6.apps.googleusercontent.com",
          "client_type": 3
        }
      ],
      "api_key": [
        {
          "current_key": "AIzaSyC0JrO1mtelIj3xpJ-TuKZrGih_ELwNsH0"
        }
      ],
      "services": {
        "appinvite_service": {
          "other_platform_oauth_client": [
            {
              "client_id": "504843835361-8ijobj1vi9mfdc2tpjanb5bllgcn17f6.apps.googleusercontent.com",
              "client_type": 3
            }
          ]
        }
      }
    }
  ],
  "configuration_version": "1"
}